Metadata-Version: 2.4
Name: razorpay-py
Version: 0.0.3
Summary: An improved Razorpay python SDK
Author: Team Razorpay, DotMyStyle (Sunserg Technologies Pvt Ltd.)
License: MIT
Project-URL: Homepage, https://github.com/sunsergdev/razorpay-python
Keywords: razorpay,payment,gateway,india
Classifier: Development Status :: 4 - Beta
Classifier: Intended Audience :: Developers
Classifier: License :: OSI Approved :: MIT License
Classifier: Operating System :: OS Independent
Classifier: Programming Language :: Python
Classifier: Programming Language :: Python :: 3
Classifier: Programming Language :: Python :: 3 :: Only
Classifier: Programming Language :: Python :: 3.9
Classifier: Programming Language :: Python :: 3.10
Classifier: Programming Language :: Python :: 3.11
Classifier: Programming Language :: Python :: 3.12
Classifier: Programming Language :: Python :: 3.13
Classifier: Topic :: Software Development :: Libraries :: Python Modules
Requires-Python: >=3.9
License-File: LICENSE
Requires-Dist: requests>=2.20
Dynamic: license-file
